LearningSparkZhongwenban38Zhang/README.md
LearningSparkZhongwenban38Zhang/__init__.py
LearningSparkZhongwenban38Zhang/__main__.py
LearningSparkZhongwenban38Zhang/file.pdf
LearningSparkZhongwenban38Zhang/index.html
learning_spark_zhongwenban_3_8_zhang-2024.3.5.0.dist-info/METADATA
learning_spark_zhongwenban_3_8_zhang-2024.3.5.0.dist-info/WHEEL
learning_spark_zhongwenban_3_8_zhang-2024.3.5.0.dist-info/entry_points.txt
learning_spark_zhongwenban_3_8_zhang-2024.3.5.0.dist-info/top_level.txt
learning_spark_zhongwenban_3_8_zhang-2024.3.5.0.dist-info/RECORD
